README.md
count-tweet
setup.py
tweet_counter/__init__.py
tweet_counter.egg-info/PKG-INFO
tweet_counter.egg-info/SOURCES.txt
tweet_counter.egg-info/dependency_links.txt
tweet_counter.egg-info/requires.txt
tweet_counter.egg-info/top_level.txt