Metadata-Version: 2.1
Name: tweet-counter
Version: 0.1.0
Summary: Calculate the length that Twitter will consider a Tweet to be
Home-page: https://github.com/nottrobin/tweet-counter
Author: Robin Winslow
Author-email: robin@robinwinslow.co.uk
License: UNKNOWN
Platform: UNKNOWN
